psiz_datasets/__init__.py
psiz_datasets/version.py
psiz_datasets/birds16_rank2019/CITATIONS.bib
psiz_datasets/birds16_rank2019/DESCRIPTION.md
psiz_datasets/birds16_rank2019/TAGS.txt
psiz_datasets/birds16_rank2019/__init__.py
psiz_datasets/birds16_rank2019/birds16_rank2019.py
psiz_datasets/birds16_rank2019/birds16_rank2019_test.py
psiz_datasets/birds16_rank2019/checksums.tsv
psiz_datasets/birds16_rank2019/dummy_data/stimuli.txt
psiz_datasets/birds16_rank2019/dummy_data/train_seqs/seq_a.json
psiz_datasets/birds16_rank2019/dummy_data/train_seqs/seq_b.json
psiz_datasets/ilsvrc2012_val_hsj/CITATIONS.bib
psiz_datasets/ilsvrc2012_val_hsj/DESCRIPTION.md
psiz_datasets/ilsvrc2012_val_hsj/TAGS.txt
psiz_datasets/ilsvrc2012_val_hsj/__init__.py
psiz_datasets/ilsvrc2012_val_hsj/checksums.tsv
psiz_datasets/ilsvrc2012_val_hsj/ilsvrc2012_val_hsj.py
psiz_datasets/ilsvrc2012_val_hsj/ilsvrc2012_val_hsj_test.py
psiz_datasets/ilsvrc2012_val_hsj/dummy_data/stimuli.txt
psiz_datasets/ilsvrc2012_val_hsj/dummy_data/test_seqs/seq_c.json
psiz_datasets/ilsvrc2012_val_hsj/dummy_data/train_seqs/seq_a.json
psiz_datasets/ilsvrc2012_val_hsj/dummy_data/train_seqs/seq_b.json
psiz_datasets/skin_lesions2018_rank2018/CITATIONS.bib
psiz_datasets/skin_lesions2018_rank2018/DESCRIPTION.md
psiz_datasets/skin_lesions2018_rank2018/TAGS.txt
psiz_datasets/skin_lesions2018_rank2018/__init__.py
psiz_datasets/skin_lesions2018_rank2018/checksums.tsv
psiz_datasets/skin_lesions2018_rank2018/skin_lesions2018_rank2018.py
psiz_datasets/skin_lesions2018_rank2018/skin_lesions2018_rank2018_test.py
psiz_datasets/skin_lesions2018_rank2018/dummy_data/stimuli.txt
psiz_datasets/skin_lesions2018_rank2018/dummy_data/train_seqs/seq_dummy_a.json
psiz_datasets/skin_lesions2018_rank2018/dummy_data/train_seqs/seq_dummy_b.json
psiz_datasets/skin_lesions2018_rank2018/dummy_data/train_seqs/seq_dummy_c.json
psiz_datasets/utils/__init__.py
psiz_datasets/utils/append_rank_placeholder.py
psiz_datasets/utils/one_hot.py
psiz_datasets-0.2.1.dist-info/LICENSE
psiz_datasets-0.2.1.dist-info/METADATA
psiz_datasets-0.2.1.dist-info/WHEEL
psiz_datasets-0.2.1.dist-info/top_level.txt
psiz_datasets-0.2.1.dist-info/RECORD
