Metadata-Version: 2.1
Name: psiz_datasets
Version: 0.2.1
Summary: Tools for managing and using PsiZ Datasets.
Home-page: https://github.com/psiz-org/psiz-datasets
Author: Brett D. Roads
Author-email: brett.roads@gmail.com
License: Apache Licence 2.0
Project-URL: Documentation, https://psiz.readthedocs.io/en/latest/
Project-URL: Source, https://github.com/psiz-org/psiz-datasets
Project-URL: Tracker, https://github.com/psiz-org/psiz-datasets/issues
Keywords: psychology,cognitive science,datasets
Classifier: Development Status :: 3 - Alpha
Classifier: Intended Audience :: Science/Research
Classifier: Topic :: Scientific/Engineering
Classifier: License :: OSI Approved :: Apache Software License
Classifier: Programming Language :: Python :: 3
Classifier: Programming Language :: Python :: 3.9
Classifier: Programming Language :: Python :: 3.10
Classifier: Programming Language :: Python :: 3.11
Classifier: Programming Language :: Python :: 3 :: Only
Requires-Python: <3.12,>=3.9
License-File: LICENSE
Requires-Dist: numpy
Requires-Dist: tensorflow<3.0,>=2.10
Requires-Dist: tensorflow-datasets
Requires-Dist: psiz>=0.8
Provides-Extra: doc
Requires-Dist: sphinx-rtd-theme==1.0.0; extra == "doc"
Requires-Dist: sphinx-last-updated-by-git; extra == "doc"
Requires-Dist: myst-nb; extra == "doc"
Requires-Dist: sphinxcontrib-bibtex; extra == "doc"
Provides-Extra: test
Requires-Dist: pytest>=6.2.4; extra == "test"
Requires-Dist: pytest-cov; extra == "test"
Requires-Dist: flake8; extra == "test"
Requires-Dist: pylint; extra == "test"
